mimetypeplus/__init__.py
mimetypeplus/cmds.py
mimetypeplus/mimetypecheckers.py
mimetypeplus/mimetypeplus.py
mimetypeplus/tools.py
mimetypeplus/typings.py
mimetypeplus-1.0.0.0.dist-info/LICENCE
mimetypeplus-1.0.0.0.dist-info/METADATA
mimetypeplus-1.0.0.0.dist-info/WHEEL
mimetypeplus-1.0.0.0.dist-info/top_level.txt
mimetypeplus-1.0.0.0.dist-info/zip-safe
mimetypeplus-1.0.0.0.dist-info/RECORD
